{
  "data":[
    {
      "id": 0,
      "title":"Haiabara’s Teenage New Game+",
      "cover":"https://cloverclubwork.github.io/BookiFab-Files/images/Img_100_0-book_reader_ReadEra.png",
      "status":"Publishing",
      "type":"Light Novel",
      "author":"Kazuki Amamiya",
      "illustrator":"Gin",
      "translation":{
        "group":"J-Novel Club",
        "link":"https://j-novel.club/series/haibara-s-teenage-new-game"
      },
      "genre":{
        "name":"Romance",
        "name":"Slice of Life",
        "name":"Seinen"
      },
      "link":"/Haibaras-Teenage-New-Game.json"
    }
  ]
}